netbox_fusioninventory_plugin/__init__.py
netbox_fusioninventory_plugin/urls.py
netbox_fusioninventory_plugin/utils.py
netbox_fusioninventory_plugin/views.py
netbox_fusioninventory_plugin-0.4.dist-info/METADATA
netbox_fusioninventory_plugin-0.4.dist-info/WHEEL
netbox_fusioninventory_plugin-0.4.dist-info/top_level.txt
netbox_fusioninventory_plugin-0.4.dist-info/RECORD
