Metadata-Version: 2.1
Name: netbox-fusioninventory-plugin
Version: 0.4
Summary: A Plugin for import devices from fusion inventory agent
Home-page: https://gitlab.com/Milka64/netbox-fusioninventory-plugin
Author: Michael Ricart
License: BSD License
Platform: UNKNOWN
Requires-Dist: bs4
Requires-Dist: lxml
